my_math_unimore/__init__.py
my_math_unimore/calculator.py
my_math_unimore/test_calculator.py
my_math_unimore/sub_folder/__init__.py
my_math_unimore/sub_folder/pippo.py
my_math_unimore-0.4.dist-info/METADATA
my_math_unimore-0.4.dist-info/WHEEL
my_math_unimore-0.4.dist-info/top_level.txt
my_math_unimore-0.4.dist-info/RECORD
